README.rst
setup.py
legacyapi/__init__.py
legacyapi/constants.py
legacyapi/contract.py
legacyapi/exceptions.py
legacyapi/lgcy.py
legacyapi/main.py
legacyapi/manager.py
legacyapi/module.py
legacyapi/transactionbuilder.py
legacyapi.egg-info/PKG-INFO
legacyapi.egg-info/SOURCES.txt
legacyapi.egg-info/dependency_links.txt
legacyapi.egg-info/not-zip-safe
legacyapi.egg-info/requires.txt
legacyapi.egg-info/top_level.txt
legacyapi/common/__init__.py
legacyapi/common/abi.py
legacyapi/common/account.py
legacyapi/common/blocks.py
legacyapi/common/contracts.py
legacyapi/common/datastructures.py
legacyapi/common/datatypes.py
legacyapi/common/encoding.py
legacyapi/common/formatters.py
legacyapi/common/normalizers.py
legacyapi/common/threads.py
legacyapi/common/transactions.py
legacyapi/common/validation.py
legacyapi/common/toolz/__init__.py
legacyapi/providers/__init__.py
legacyapi/providers/base.py
legacyapi/providers/http.py