Metadata-Version: 2.1
Name: legacyapi
Version: 3.1.5
Summary: A Python API for interacting with Legacy (LGCY)
Home-page: https://github.com/autotheos/legacy-api-python
Author: Shamsudin Serderov
Author-email: steein.shamsudin@gmail.com
License: MIT License
Keywords: legayc legacy-api legacy-api-python iexbase
Platform: UNKNOWN
Classifier: Development Status :: 3 - Alpha
Classifier: Intended Audience :: Developers
Classifier: License :: OSI Approved :: MIT License
Classifier: Natural Language :: English
Classifier: Programming Language :: Python :: 3
Classifier: Programming Language :: Python :: 3.6
Classifier: Programming Language :: Python :: 3.7
Requires-Python: >=3.6,<4
Provides-Extra: dev
Provides-Extra: docs
Provides-Extra: tester
